nonlineartemppy/__init__.py
nonlineartemppy/calculations.py
nonlineartemppy-0.201.dist-info/METADATA
nonlineartemppy-0.201.dist-info/WHEEL
nonlineartemppy-0.201.dist-info/top_level.txt
nonlineartemppy-0.201.dist-info/RECORD
