Metadata-Version: 2.1
Name: nonlineartemppy
Version: 0.201
Summary: Calculate daily degree days and time in each degree
Home-page: https://github.com/johnwoodill/nonlineartemppy
Author: A. John Woodill
Author-email: johnwoodill@gmail.com
License: UNKNOWN
Project-URL: Bug Reports, https://github.com/johnwoodill/nonlineartemppy/issues
Project-URL: Source, https://github.com/johnwoodill/nonlineartemppy
Keywords: nonlinear temperature degreedays timeineachdegree
Platform: UNKNOWN
Classifier: Development Status :: 3 - Alpha
Classifier: Intended Audience :: Developers
Classifier: Topic :: Software Development :: Build Tools
Classifier: License :: OSI Approved :: MIT License
Classifier: Programming Language :: Python :: 3.6
Requires-Dist: numpy
